bids_pydantic_models/__init__.py
bids_pydantic_models/bids_metadata_v1_7_0.py
bids_pydantic_models/bids_metadata_v1_8_0.py
bids_pydantic_models/py.typed
BIDS_pydantic_models-0.0.3.dist-info/LICENSE
BIDS_pydantic_models-0.0.3.dist-info/METADATA
BIDS_pydantic_models-0.0.3.dist-info/WHEEL
BIDS_pydantic_models-0.0.3.dist-info/top_level.txt
BIDS_pydantic_models-0.0.3.dist-info/RECORD
