Metadata-Version: 2.1
Name: BIDS-pydantic-models
Version: 0.0.3
Summary: Pydantic models for BIDS metadata
Home-page: https://github.com/gold-standard-phantoms/bids-pydantic
Author: Gold Standard Phantoms
Author-email: tom.hampshire@goldstandardphantoms.com
License: MIT
Project-URL: Documentation, https://github.com/gold-standard-phantoms/bids-pydantic
Project-URL: Code, https://github.com/gold-standard-phantoms/bids-pydantic
Project-URL: Issue tracker, https://github.com/gold-standard-phantoms/bids-pydantic/issues
Platform: UNKNOWN
Classifier: Development Status :: 5 - Production/Stable
Classifier: Intended Audience :: Science/Research
Classifier: Topic :: Scientific/Engineering
Classifier: Programming Language :: Python :: 3
Classifier: License :: OSI Approved :: MIT License
Classifier: Operating System :: OS Independent
Requires-Python: >=3.9
License-File: LICENSE
Requires-Dist: pydantic (<2.0,>=1.9.1)
